django_changelist_toolbar_admin/__init__.py
django_changelist_toolbar_admin/admin.py
django_changelist_toolbar_admin/apps.py
django_changelist_toolbar_admin/models.py
django_changelist_toolbar_admin/tests.py
django_changelist_toolbar_admin/views.py
django_changelist_toolbar_admin/migrations/__init__.py
django_changelist_toolbar_admin/static/django-changelist-toolbar-admin/css/django-changelist-toolbar-admin.css
django_changelist_toolbar_admin/templates/admin/change_list_object_tools.html
django_changelist_toolbar_admin-0.4.7.dist-info/licenses/LICENSE
django_changelist_toolbar_admin-0.4.7.dist-info/METADATA
django_changelist_toolbar_admin-0.4.7.dist-info/WHEEL
django_changelist_toolbar_admin-0.4.7.dist-info/top_level.txt
django_changelist_toolbar_admin-0.4.7.dist-info/RECORD
